{
  "frame_index": 205,
  "video_name": "19_경사진 침대에서 다리 구부리기 (양쪽).MOV",
  "meta_info": {
    "dataset_name": "coco",
    "num_keypoints": 17,
    "keypoint_id2name": {
      "0": "nose",
      "1": "left_eye",
      "2": "right_eye",
      "3": "left_ear",
      "4": "right_ear",
      "5": "left_shoulder",
      "6": "right_shoulder",
      "7": "left_elbow",
      "8": "right_elbow",
      "9": "left_wrist",
      "10": "right_wrist",
      "11": "left_hip",
      "12": "right_hip",
      "13": "left_knee",
      "14": "right_knee",
      "15": "left_ankle",
      "16": "right_ankle"
    },
    "keypoint_name2id": {
      "nose": 0,
      "left_eye": 1,
      "right_eye": 2,
      "left_ear": 3,
      "right_ear": 4,
      "left_shoulder": 5,
      "right_shoulder": 6,
      "left_elbow": 7,
      "right_elbow": 8,
      "left_wrist": 9,
      "right_wrist": 10,
      "left_hip": 11,
      "right_hip": 12,
      "left_knee": 13,
      "right_knee": 14,
      "left_ankle": 15,
      "right_ankle": 16
    },
    "upper_body_ids": [
      0,
      1,
      2,
      3,
      4,
      5,
      6,
      7,
      8,
      9,
      10
    ],
    "lower_body_ids": [
      11,
      12,
      13,
      14,
      15,
      16
    ],
    "flip_indices": [
      0,
      2,
      1,
      4,
      3,
      6,
      5,
      8,
      7,
      10,
      9,
      12,
      11,
      14,
      13,
      16,
      15
    ],
    "flip_pairs": [
      [
        2,
        1
      ],
      [
        1,
        2
      ],
      [
        4,
        3
      ],
      [
        3,
        4
      ],
      [
        6,
        5
      ],
      [
        5,
        6
      ],
      [
        8,
        7
      ],
      [
        7,
        8
      ],
      [
        10,
        9
      ],
      [
        9,
        10
      ],
      [
        12,
        11
      ],
      [
        11,
        12
      ],
      [
        14,
        13
      ],
      [
        13,
        14
      ],
      [
        16,
        15
      ],
      [
        15,
        16
      ]
    ],
    "keypoint_colors": [
      [
        51,
        153,
        255
      ],
      [
        51,
        153,
        255
      ],
      [
        51,
        153,
        255
      ],
      [
        51,
        153,
        255
      ],
      [
        51,
        153,
        255
      ],
      [
        0,
        255,
        0
      ],
      [
        255,
        128,
        0
      ],
      [
        0,
        255,
        0
      ],
      [
        255,
        128,
        0
      ],
      [
        0,
        255,
        0
      ],
      [
        255,
        128,
        0
      ],
      [
        0,
        255,
        0
      ],
      [
        255,
        128,
        0
      ],
      [
        0,
        255,
        0
      ],
      [
        255,
        128,
        0
      ],
      [
        0,
        255,
        0
      ],
      [
        255,
        128,
        0
      ]
    ],
    "num_skeleton_links": 19,
    "skeleton_links": [
      [
        15,
        13
      ],
      [
        13,
        11
      ],
      [
        16,
        14
      ],
      [
        14,
        12
      ],
      [
        11,
        12
      ],
      [
        5,
        11
      ],
      [
        6,
        12
      ],
      [
        5,
        6
      ],
      [
        5,
        7
      ],
      [
        6,
        8
      ],
      [
        7,
        9
      ],
      [
        8,
        10
      ],
      [
        1,
        2
      ],
      [
        0,
        1
      ],
      [
        0,
        2
      ],
      [
        1,
        3
      ],
      [
        2,
        4
      ],
      [
        3,
        5
      ],
      [
        4,
        6
      ]
    ],
    "skeleton_link_colors": [
      [
        0,
        255,
        0
      ],
      [
        0,
        255,
        0
      ],
      [
        255,
        128,
        0
      ],
      [
        255,
        128,
        0
      ],
      [
        51,
        153,
        255
      ],
      [
        51,
        153,
        255
      ],
      [
        51,
        153,
        255
      ],
      [
        51,
        153,
        255
      ],
      [
        0,
        255,
        0
      ],
      [
        255,
        128,
        0
      ],
      [
        0,
        255,
        0
      ],
      [
        255,
        128,
        0
      ],
      [
        51,
        153,
        255
      ],
      [
        51,
        153,
        255
      ],
      [
        51,
        153,
        255
      ],
      [
        51,
        153,
        255
      ],
      [
        51,
        153,
        255
      ],
      [
        51,
        153,
        255
      ],
      [
        51,
        153,
        255
      ]
    ],
    "dataset_keypoint_weights": [
      1.0,
      1.0,
      1.0,
      1.0,
      1.0,
      1.0,
      1.0,
      1.2000000476837158,
      1.2000000476837158,
      1.5,
      1.5,
      1.0,
      1.0,
      1.2000000476837158,
      1.2000000476837158,
      1.5,
      1.5
    ],
    "sigmas": [
      0.026000000536441803,
      0.02500000037252903,
      0.02500000037252903,
      0.03500000014901161,
      0.03500000014901161,
      0.07900000363588333,
      0.07900000363588333,
      0.07199999690055847,
      0.07199999690055847,
      0.06199999898672104,
      0.06199999898672104,
      0.10700000077486038,
      0.10700000077486038,
      0.08699999749660492,
      0.08699999749660492,
      0.08900000154972076,
      0.08900000154972076
    ]
  },
  "instance_info": [
    {
      "keypoints": [
        [
          327.166815736648,
          544.2037907748382
        ],
        [
          336.4361923124218,
          539.4666476353099
        ],
        [
          319.2694899339731,
          538.9170037991112
        ],
        [
          354.46077859314664,
          546.4802915890217
        ],
        [
          304.6010750771783,
          545.1584821883818
        ],
        [
          377.83071937929617,
          604.4718653721205
        ],
        [
          276.2190858183468,
          603.61513583568
        ],
        [
          409.12232965643943,
          677.4038399076819
        ],
        [
          238.95367529537987,
          676.399469633541
        ],
        [
          420.3076161325017,
          737.6063977598267
        ],
        [
          240.12320683138796,
          741.3648673455853
        ],
        [
          368.3465196588638,
          733.9986793360054
        ],
        [
          299.0708978314158,
          736.6633566985474
        ],
        [
          363.87637137281047,
          851.1380254463202
        ],
        [
          259.2694516625031,
          662.3316912565508
        ],
        [
          387.2445513135119,
          1034.5885168459522
        ],
        [
          264.1929736302858,
          809.8193697063252
        ]
      ],
      "keypoint_scores": [
        0.04709617793560028,
        0.041557230055332184,
        0.041638053953647614,
        0.045802950859069824,
        0.03967856615781784,
        0.09956283122301102,
        0.09501542150974274,
        0.10126625746488571,
        0.06290322542190552,
        0.12362255156040192,
        0.1170162484049797,
        0.07756446301937103,
        0.06609071791172028,
        0.05027586966753006,
        0.06330128014087677,
        0.03566010296344757,
        0.05636456608772278
      ],
      "bbox": [
        [
          209.39427185058594,
          494.2847900390625,
          449.0421142578125,
          1082.0491943359375
        ]
      ],
      "bbox_score": 1.0
    }
  ]
}