{
  "frame_index": 39,
  "video_name": "20_경사진 침대에서 무릎 펴서 다리 들기 (양쪽).MOV",
  "meta_info": {
    "dataset_name": "coco",
    "num_keypoints": 17,
    "keypoint_id2name": {
      "0": "nose",
      "1": "left_eye",
      "2": "right_eye",
      "3": "left_ear",
      "4": "right_ear",
      "5": "left_shoulder",
      "6": "right_shoulder",
      "7": "left_elbow",
      "8": "right_elbow",
      "9": "left_wrist",
      "10": "right_wrist",
      "11": "left_hip",
      "12": "right_hip",
      "13": "left_knee",
      "14": "right_knee",
      "15": "left_ankle",
      "16": "right_ankle"
    },
    "keypoint_name2id": {
      "nose": 0,
      "left_eye": 1,
      "right_eye": 2,
      "left_ear": 3,
      "right_ear": 4,
      "left_shoulder": 5,
      "right_shoulder": 6,
      "left_elbow": 7,
      "right_elbow": 8,
      "left_wrist": 9,
      "right_wrist": 10,
      "left_hip": 11,
      "right_hip": 12,
      "left_knee": 13,
      "right_knee": 14,
      "left_ankle": 15,
      "right_ankle": 16
    },
    "upper_body_ids": [
      0,
      1,
      2,
      3,
      4,
      5,
      6,
      7,
      8,
      9,
      10
    ],
    "lower_body_ids": [
      11,
      12,
      13,
      14,
      15,
      16
    ],
    "flip_indices": [
      0,
      2,
      1,
      4,
      3,
      6,
      5,
      8,
      7,
      10,
      9,
      12,
      11,
      14,
      13,
      16,
      15
    ],
    "flip_pairs": [
      [
        2,
        1
      ],
      [
        1,
        2
      ],
      [
        4,
        3
      ],
      [
        3,
        4
      ],
      [
        6,
        5
      ],
      [
        5,
        6
      ],
      [
        8,
        7
      ],
      [
        7,
        8
      ],
      [
        10,
        9
      ],
      [
        9,
        10
      ],
      [
        12,
        11
      ],
      [
        11,
        12
      ],
      [
        14,
        13
      ],
      [
        13,
        14
      ],
      [
        16,
        15
      ],
      [
        15,
        16
      ]
    ],
    "keypoint_colors": [
      [
        51,
        153,
        255
      ],
      [
        51,
        153,
        255
      ],
      [
        51,
        153,
        255
      ],
      [
        51,
        153,
        255
      ],
      [
        51,
        153,
        255
      ],
      [
        0,
        255,
        0
      ],
      [
        255,
        128,
        0
      ],
      [
        0,
        255,
        0
      ],
      [
        255,
        128,
        0
      ],
      [
        0,
        255,
        0
      ],
      [
        255,
        128,
        0
      ],
      [
        0,
        255,
        0
      ],
      [
        255,
        128,
        0
      ],
      [
        0,
        255,
        0
      ],
      [
        255,
        128,
        0
      ],
      [
        0,
        255,
        0
      ],
      [
        255,
        128,
        0
      ]
    ],
    "num_skeleton_links": 19,
    "skeleton_links": [
      [
        15,
        13
      ],
      [
        13,
        11
      ],
      [
        16,
        14
      ],
      [
        14,
        12
      ],
      [
        11,
        12
      ],
      [
        5,
        11
      ],
      [
        6,
        12
      ],
      [
        5,
        6
      ],
      [
        5,
        7
      ],
      [
        6,
        8
      ],
      [
        7,
        9
      ],
      [
        8,
        10
      ],
      [
        1,
        2
      ],
      [
        0,
        1
      ],
      [
        0,
        2
      ],
      [
        1,
        3
      ],
      [
        2,
        4
      ],
      [
        3,
        5
      ],
      [
        4,
        6
      ]
    ],
    "skeleton_link_colors": [
      [
        0,
        255,
        0
      ],
      [
        0,
        255,
        0
      ],
      [
        255,
        128,
        0
      ],
      [
        255,
        128,
        0
      ],
      [
        51,
        153,
        255
      ],
      [
        51,
        153,
        255
      ],
      [
        51,
        153,
        255
      ],
      [
        51,
        153,
        255
      ],
      [
        0,
        255,
        0
      ],
      [
        255,
        128,
        0
      ],
      [
        0,
        255,
        0
      ],
      [
        255,
        128,
        0
      ],
      [
        51,
        153,
        255
      ],
      [
        51,
        153,
        255
      ],
      [
        51,
        153,
        255
      ],
      [
        51,
        153,
        255
      ],
      [
        51,
        153,
        255
      ],
      [
        51,
        153,
        255
      ],
      [
        51,
        153,
        255
      ]
    ],
    "dataset_keypoint_weights": [
      1.0,
      1.0,
      1.0,
      1.0,
      1.0,
      1.0,
      1.0,
      1.2000000476837158,
      1.2000000476837158,
      1.5,
      1.5,
      1.0,
      1.0,
      1.2000000476837158,
      1.2000000476837158,
      1.5,
      1.5
    ],
    "sigmas": [
      0.026000000536441803,
      0.02500000037252903,
      0.02500000037252903,
      0.03500000014901161,
      0.03500000014901161,
      0.07900000363588333,
      0.07900000363588333,
      0.07199999690055847,
      0.07199999690055847,
      0.06199999898672104,
      0.06199999898672104,
      0.10700000077486038,
      0.10700000077486038,
      0.08699999749660492,
      0.08699999749660492,
      0.08900000154972076,
      0.08900000154972076
    ]
  },
  "instance_info": [
    {
      "keypoints": [
        [
          328.18285524923135,
          545.2279776308995
        ],
        [
          338.6703221984792,
          541.848853922702
        ],
        [
          319.9715448970521,
          541.4422673623169
        ],
        [
          354.2729554051797,
          548.8362626393646
        ],
        [
          304.9605577803602,
          548.3230424115252
        ],
        [
          379.39759544169533,
          607.2819327374792
        ],
        [
          276.22664616443706,
          604.2703811740229
        ],
        [
          410.8388699175721,
          680.383656271295
        ],
        [
          244.22676112805618,
          675.707604346479
        ],
        [
          419.53018608273874,
          738.9140547544312
        ],
        [
          239.09901811100087,
          740.3410059312341
        ],
        [
          367.8364307124616,
          728.6276696393265
        ],
        [
          291.3708737120569,
          722.1761391917828
        ],
        [
          357.73244725335974,
          851.376441494054
        ],
        [
          273.30724430611326,
          789.0420299486677
        ],
        [
          374.44704690753565,
          1040.9947173481296
        ],
        [
          232.76664118658925,
          908.562928854853
        ]
      ],
      "keypoint_scores": [
        0.04658949747681618,
        0.04118426889181137,
        0.04226263612508774,
        0.04258028417825699,
        0.036879848688840866,
        0.09289376437664032,
        0.08881272375583649,
        0.09478972852230072,
        0.08369685709476471,
        0.11582928895950317,
        0.07738781720399857,
        0.08584734797477722,
        0.07884581387042999,
        0.05606929212808609,
        0.04878177493810654,
        0.03485832363367081,
        0.07555563002824783
      ],
      "bbox": [
        [
          160.9446563720703,
          497.43890380859375,
          449.117919921875,
          1072.5184326171875
        ]
      ],
      "bbox_score": 1.0
    }
  ]
}