{
  "frame_index": 302,
  "video_name": "20_경사진 침대에서 무릎 펴서 다리 들기 (양쪽).MOV",
  "meta_info": {
    "dataset_name": "coco",
    "num_keypoints": 17,
    "keypoint_id2name": {
      "0": "nose",
      "1": "left_eye",
      "2": "right_eye",
      "3": "left_ear",
      "4": "right_ear",
      "5": "left_shoulder",
      "6": "right_shoulder",
      "7": "left_elbow",
      "8": "right_elbow",
      "9": "left_wrist",
      "10": "right_wrist",
      "11": "left_hip",
      "12": "right_hip",
      "13": "left_knee",
      "14": "right_knee",
      "15": "left_ankle",
      "16": "right_ankle"
    },
    "keypoint_name2id": {
      "nose": 0,
      "left_eye": 1,
      "right_eye": 2,
      "left_ear": 3,
      "right_ear": 4,
      "left_shoulder": 5,
      "right_shoulder": 6,
      "left_elbow": 7,
      "right_elbow": 8,
      "left_wrist": 9,
      "right_wrist": 10,
      "left_hip": 11,
      "right_hip": 12,
      "left_knee": 13,
      "right_knee": 14,
      "left_ankle": 15,
      "right_ankle": 16
    },
    "upper_body_ids": [
      0,
      1,
      2,
      3,
      4,
      5,
      6,
      7,
      8,
      9,
      10
    ],
    "lower_body_ids": [
      11,
      12,
      13,
      14,
      15,
      16
    ],
    "flip_indices": [
      0,
      2,
      1,
      4,
      3,
      6,
      5,
      8,
      7,
      10,
      9,
      12,
      11,
      14,
      13,
      16,
      15
    ],
    "flip_pairs": [
      [
        2,
        1
      ],
      [
        1,
        2
      ],
      [
        4,
        3
      ],
      [
        3,
        4
      ],
      [
        6,
        5
      ],
      [
        5,
        6
      ],
      [
        8,
        7
      ],
      [
        7,
        8
      ],
      [
        10,
        9
      ],
      [
        9,
        10
      ],
      [
        12,
        11
      ],
      [
        11,
        12
      ],
      [
        14,
        13
      ],
      [
        13,
        14
      ],
      [
        16,
        15
      ],
      [
        15,
        16
      ]
    ],
    "keypoint_colors": [
      [
        51,
        153,
        255
      ],
      [
        51,
        153,
        255
      ],
      [
        51,
        153,
        255
      ],
      [
        51,
        153,
        255
      ],
      [
        51,
        153,
        255
      ],
      [
        0,
        255,
        0
      ],
      [
        255,
        128,
        0
      ],
      [
        0,
        255,
        0
      ],
      [
        255,
        128,
        0
      ],
      [
        0,
        255,
        0
      ],
      [
        255,
        128,
        0
      ],
      [
        0,
        255,
        0
      ],
      [
        255,
        128,
        0
      ],
      [
        0,
        255,
        0
      ],
      [
        255,
        128,
        0
      ],
      [
        0,
        255,
        0
      ],
      [
        255,
        128,
        0
      ]
    ],
    "num_skeleton_links": 19,
    "skeleton_links": [
      [
        15,
        13
      ],
      [
        13,
        11
      ],
      [
        16,
        14
      ],
      [
        14,
        12
      ],
      [
        11,
        12
      ],
      [
        5,
        11
      ],
      [
        6,
        12
      ],
      [
        5,
        6
      ],
      [
        5,
        7
      ],
      [
        6,
        8
      ],
      [
        7,
        9
      ],
      [
        8,
        10
      ],
      [
        1,
        2
      ],
      [
        0,
        1
      ],
      [
        0,
        2
      ],
      [
        1,
        3
      ],
      [
        2,
        4
      ],
      [
        3,
        5
      ],
      [
        4,
        6
      ]
    ],
    "skeleton_link_colors": [
      [
        0,
        255,
        0
      ],
      [
        0,
        255,
        0
      ],
      [
        255,
        128,
        0
      ],
      [
        255,
        128,
        0
      ],
      [
        51,
        153,
        255
      ],
      [
        51,
        153,
        255
      ],
      [
        51,
        153,
        255
      ],
      [
        51,
        153,
        255
      ],
      [
        0,
        255,
        0
      ],
      [
        255,
        128,
        0
      ],
      [
        0,
        255,
        0
      ],
      [
        255,
        128,
        0
      ],
      [
        51,
        153,
        255
      ],
      [
        51,
        153,
        255
      ],
      [
        51,
        153,
        255
      ],
      [
        51,
        153,
        255
      ],
      [
        51,
        153,
        255
      ],
      [
        51,
        153,
        255
      ],
      [
        51,
        153,
        255
      ]
    ],
    "dataset_keypoint_weights": [
      1.0,
      1.0,
      1.0,
      1.0,
      1.0,
      1.0,
      1.0,
      1.2000000476837158,
      1.2000000476837158,
      1.5,
      1.5,
      1.0,
      1.0,
      1.2000000476837158,
      1.2000000476837158,
      1.5,
      1.5
    ],
    "sigmas": [
      0.026000000536441803,
      0.02500000037252903,
      0.02500000037252903,
      0.03500000014901161,
      0.03500000014901161,
      0.07900000363588333,
      0.07900000363588333,
      0.07199999690055847,
      0.07199999690055847,
      0.06199999898672104,
      0.06199999898672104,
      0.10700000077486038,
      0.10700000077486038,
      0.08699999749660492,
      0.08699999749660492,
      0.08900000154972076,
      0.08900000154972076
    ]
  },
  "instance_info": [
    {
      "keypoints": [
        [
          329.2221746580208,
          551.0324885481348
        ],
        [
          337.8929775396109,
          544.4990533530859
        ],
        [
          320.8412415668056,
          544.3128299215115
        ],
        [
          355.4685234771554,
          550.0994507473547
        ],
        [
          306.43355645660154,
          550.2850821999505
        ],
        [
          379.4663331271272,
          611.75663976429
        ],
        [
          277.20109830370075,
          606.595109274567
        ],
        [
          412.4451534912498,
          679.4497385324946
        ],
        [
          244.73686728933683,
          676.6706471747189
        ],
        [
          422.3418766514286,
          739.8476698661843
        ],
        [
          239.74190208667414,
          738.8676947099466
        ],
        [
          368.9877364724455,
          735.3619425784138
        ],
        [
          289.87262064690526,
          731.8930773147911
        ],
        [
          364.53228262460334,
          860.1789474311704
        ],
        [
          264.00057610675344,
          859.7123627553383
        ],
        [
          372.84661653104445,
          1046.1267009727512
        ],
        [
          220.60701843284323,
          1055.3724654518799
        ]
      ],
      "keypoint_scores": [
        0.03771578148007393,
        0.030659552663564682,
        0.031586602330207825,
        0.03329058364033699,
        0.028802430257201195,
        0.08482252061367035,
        0.08708134293556213,
        0.09690344333648682,
        0.08907090127468109,
        0.11346438527107239,
        0.10373932123184204,
        0.07294492423534393,
        0.07406902313232422,
        0.059341154992580414,
        0.055401019752025604,
        0.053833067417144775,
        0.06771418452262878
      ],
      "bbox": [
        [
          164.27037048339844,
          498.4964904785156,
          449.463623046875,
          1201.99609375
        ]
      ],
      "bbox_score": 1.0
    }
  ]
}